_nnef.cpython-311-darwin.so
nnef/binary.py
nnef/shapes.py
nnef/nnef.cpp
nnef/__init__.py
nnef/parser.py
nnef/validate.py
nnef/printer.py
nnef/cpp/CMakeLists.txt
nnef/cpp/infer.cpp
nnef/cpp/sample.cpp
nnef/cpp/include/nnef.h
nnef/cpp/include/cnnef.h
nnef/cpp/include/nnef/flat/stdlib_protos.h
nnef/cpp/include/nnef/flat/quant_parser.h
nnef/cpp/include/nnef/flat/flat_parser.h
nnef/cpp/include/nnef/runtime/operations.h
nnef/cpp/include/nnef/runtime/execution.h
nnef/cpp/include/nnef/runtime/ndrange.h
nnef/cpp/include/nnef/comp/evaluation.h
nnef/cpp/include/nnef/comp/expression.h
nnef/cpp/include/nnef/comp/fragment.h
nnef/cpp/include/nnef/comp/stdlib_source.h
nnef/cpp/include/nnef/comp/comp_parser.h
nnef/cpp/include/nnef/common/error.h
nnef/cpp/include/nnef/common/parser.h
nnef/cpp/include/nnef/common/value.h
nnef/cpp/include/nnef/common/dictionary.h
nnef/cpp/include/nnef/common/typeutils.h
nnef/cpp/include/nnef/common/typespec.h
nnef/cpp/include/nnef/common/lexer.h
nnef/cpp/include/nnef/common/shapes.h
nnef/cpp/include/nnef/common/binary.h
nnef/cpp/include/nnef/common/prototype.h
nnef/cpp/src/nnef.cpp
nnef/cpp/src/cnnef.cpp
nnef-1.0.9.dist-info/RECORD
nnef-1.0.9.dist-info/WHEEL
nnef-1.0.9.dist-info/top_level.txt
nnef-1.0.9.dist-info/METADATA
