Metadata-Version: 2.4
Name: nnef
Version: 1.0.9
Summary: A package for parsing NNEF files
Author-email: Khronos Group <nnef@lists.khronos.org>
Maintainer-email: Viktor Gyenes <viktor.gyenes@aimotive.com>
Project-URL: Homepage, https://www.khronos.org/nnef
Project-URL: Repository, https://github.com/KhronosGroup/NNEF-Tools
Keywords: nnef
Classifier: Development Status :: 4 - Beta
Classifier: Intended Audience :: Developers
Classifier: License :: OSI Approved :: Apache Software License
Classifier: Programming Language :: Python :: 2
Classifier: Programming Language :: Python :: 3
Requires-Python: >=3.7
Requires-Dist: numpy
